CHANGELOG.md
LICENSE
MANIFEST.in
README.md
setup.cfg
setup.py
TracMultiSelectBoxPlugin.egg-info/PKG-INFO
TracMultiSelectBoxPlugin.egg-info/SOURCES.txt
TracMultiSelectBoxPlugin.egg-info/dependency_links.txt
TracMultiSelectBoxPlugin.egg-info/entry_points.txt
TracMultiSelectBoxPlugin.egg-info/requires.txt
TracMultiSelectBoxPlugin.egg-info/top_level.txt
multiselectbox/__init__.py
multiselectbox/filter.py
multiselectbox/locale/messages.pot
multiselectbox/locale/ja/LC_MESSAGES/multiselectbox.po
patch/support-multipleselct-for-reverthandler-trac10.patch