Metadata-Version: 1.1
Name: TracMultiSelectBoxPlugin
Version: 0.5.1
Summary: Provide simple multiple select values field
Home-page: http://trac-hacks.org/wiki/TracMultiSelectBoxPlugin
Author: Tetsuya Morimoto
Author-email: tetsuya dot morimoto at gmail dot com
License: Apache License 2.0
Keywords: trac,plugin,ticket,multiselect
Platform: UNKNOWN
Classifier: Framework :: Trac
Classifier: Development Status :: 4 - Beta
Classifier: Environment :: Web Environment
Classifier: License :: OSI Approved :: Apache Software License
Classifier: Intended Audience :: Developers
Classifier: Operating System :: OS Independent
Classifier: Programming Language :: Python
Classifier: Topic :: Software Development
